bsstudio/__init__.py
bsstudio/bluesky_widgets_conversion.py
bsstudio/functions.py
bsstudio/git.py
bsstudio/qtplugins.py
bsstudio/shared.py
bsstudio/test.py
bsstudio/window.py
bsstudio/worker.py
bsstudio/lib/__init__.py
bsstudio/lib/pydollarmacro/__init__.py
bsstudio/lib/pydollarmacro/setup.py
bsstudio/lib/pydollarmacro/pydollarmacro/__init__.py
bsstudio/widgets/Base.py
bsstudio/widgets/CodeButton.py
bsstudio/widgets/CodeObject.py
bsstudio/widgets/REAbortButton.py
bsstudio/widgets/REButton.py
bsstudio/widgets/TextUpdate.py
bsstudio/widgets/__init__.py
bsstudio/widgets/arrayimage.py
bsstudio/widgets/barupdate.py
bsstudio/widgets/booleanled.py
bsstudio/widgets/channelsbox.py
bsstudio/widgets/databrowser.py
bsstudio/widgets/embedframe.py
bsstudio/widgets/lineinput.py
bsstudio/widgets/mplwidget.py
bsstudio/widgets/ophydproperties.py
bsstudio/widgets/ut.py
bsstudio-1.0.1.dist-info/LICENSE
bsstudio-1.0.1.dist-info/METADATA
bsstudio-1.0.1.dist-info/WHEEL
bsstudio-1.0.1.dist-info/top_level.txt
bsstudio-1.0.1.dist-info/RECORD
