Metadata-Version: 2.1
Name: bsstudio
Version: 1.0.1
Summary: Bluesky widgets for PyQt
Home-page: UNKNOWN
Author: Bayan Alexander Sobhani
Author-email: bsobhani@bnl.gov
License: UNKNOWN
Platform: UNKNOWN
Classifier: Programming Language :: Python :: 3
Classifier: License :: OSI Approved :: MIT License
Classifier: Operating System :: OS Independent
Requires-Python: >=3.6
